{
	"song": {
		"player1": "bf",
		"player2": "n_freddy",
		"events": [
			[
				109629.629629629,
				[
					[
						"Change Character",
						"bf",
						"bf-blueballed"
					],
					[
						"Play Animation",
						"firstDeath",
						"bf"
					]
				]
			],
			[
				112129.629629629,
				[
					[
						"Play Animation",
						"retryLoop",
						"bf"
					]
				]
			]
		],
		"notes": [
			{
				"lengthInSteps": 16,
				"typeOfSection": 0,
				"sectionNotes": [
					[
						0,
						0,
						0
					],
					[
						185.185185185185,
						1,
						0
					],
					[
						370.37037037037,
						2,
						0
					],
					[
						555.555555555555,
						3,
						0
					],
					[
						740.740740740741,
						0,
						0
					],
					[
						833.333333333333,
						0,
						0
					],
					[
						1111.11111111111,
						3,
						277.777777777778
					],
					[
						925.925925925926,
						2,
						0
					],
					[
						1018.51851851852,
						1,
						0
					],
					[
						1134.25925925926,
						2,
						0
					]
				],
				"altAnim": false,
				"gfSection": false,
				"bpm": 150,
				"changeBPM": false,
				"mustHitSection": false
			},
			{
				"lengthInSteps": 16,
				"typeOfSection": 0,
				"sectionNotes": [
					[
						1481.48148148148,
						0,
						0
					],
					[
						1666.66666666667,
						2,
						0
					],
					[
						1851.85185185185,
						1,
						0
					],
					[
						2037.03703703704,
						3,
						0
					],
					[
						2037.03703703704,
						2,
						0
					],
					[
						2222.22222222222,
						0,
						0
					],
					[
						2407.40740740741,
						1,
						0
					],
					[
						2592.59259259259,
						3,
						0
					],
					[
						2685.18518518519,
						2,
						0
					],
					[
						2777.77777777778,
						3,
						0
					],
					[
						2870.37037037037,
						0,
						0
					],
					[
						2870.37037037037,
						1,
						0
					]
				],
				"altAnim": false,
				"gfSection": false,
				"bpm": 150,
				"changeBPM": false,
				"mustHitSection": false
			},
			{
				"lengthInSteps": 16,
				"typeOfSection": 0,
				"sectionNotes": [
					[
						2962.96296296296,
						0,
						0
					],
					[
						3148.14814814815,
						1,
						0
					],
					[
						3333.33333333333,
						2,
						0
					],
					[
						3518.51851851852,
						3,
						0
					],
					[
						3703.7037037037,
						0,
						0
					],
					[
						3796.2962962963,
						0,
						0
					],
					[
						4074.07407407407,
						3,
						277.777777777778
					],
					[
						3888.88888888889,
						2,
						0
					],
					[
						3981.48148148148,
						1,
						0
					],
					[
						4097.22222222222,
						2,
						0
					]
				],
				"altAnim": false,
				"gfSection": false,
				"bpm": 155,
				"changeBPM": false,
				"mustHitSection": true
			},
			{
				"lengthInSteps": 16,
				"typeOfSection": 0,
				"sectionNotes": [
					[
						4444.44444444444,
						0,
						0
					],
					[
						4629.62962962963,
						2,
						0
					],
					[
						4814.81481481481,
						1,
						0
					],
					[
						5000,
						3,
						0
					],
					[
						5000,
						2,
						0
					],
					[
						5185.18518518518,
						0,
						0
					],
					[
						5370.37037037037,
						1,
						0
					],
					[
						5555.55555555555,
						3,
						0
					],
					[
						5648.14814814815,
						2,
						0
					],
					[
						5740.74074074074,
						3,
						0
					],
					[
						5833.33333333333,
						0,
						0
					],
					[
						5833.33333333333,
						1,
						0
					]
				],
				"altAnim": false,
				"gfSection": false,
				"bpm": 155,
				"changeBPM": false,
				"mustHitSection": true
			},
			{
				"lengthInSteps": 16,
				"typeOfSection": 0,
				"sectionNotes": [
					[
						5925.92592592593,
						0,
						0
					],
					[
						6666.66666666667,
						0,
						0
					],
					[
						6111.11111111111,
						3,
						0
					],
					[
						6203.7037037037,
						2,
						0
					],
					[
						6296.2962962963,
						1,
						0
					],
					[
						6388.88888888889,
						0,
						0
					],
					[
						7037.03703703704,
						3,
						0
					],
					[
						7222.22222222222,
						0,
						0
					],
					[
						6759.25925925926,
						1,
						0
					],
					[
						6851.85185185185,
						2,
						0
					],
					[
						6944.44444444444,
						0,
						0
					],
					[
						7222.22222222222,
						2,
						0
					]
				],
				"altAnim": false,
				"gfSection": false,
				"bpm": 165,
				"changeBPM": false,
				"mustHitSection": false
			},
			{
				"lengthInSteps": 16,
				"typeOfSection": 0,
				"sectionNotes": [
					[
						7407.40740740741,
						0,
						0
					],
					[
						7592.59259259259,
						1,
						0
					],
					[
						7777.77777777778,
						2,
						0
					],
					[
						7962.96296296296,
						0,
						0
					],
					[
						8148.14814814815,
						3,
						0
					],
					[
						8333.33333333333,
						2,
						0
					],
					[
						8518.51851851852,
						1,
						0
					],
					[
						8611.11111111111,
						2,
						0
					],
					[
						8703.7037037037,
						3,
						0
					]
				],
				"altAnim": false,
				"gfSection": false,
				"bpm": 165,
				"changeBPM": false,
				"mustHitSection": false
			},
			{
				"lengthInSteps": 16,
				"typeOfSection": 0,
				"sectionNotes": [
					[
						8888.88888888889,
						0,
						0
					],
					[
						9629.62962962963,
						0,
						0
					],
					[
						9074.07407407407,
						3,
						0
					],
					[
						9166.66666666667,
						2,
						0
					],
					[
						9259.25925925926,
						1,
						0
					],
					[
						9351.85185185185,
						0,
						0
					],
					[
						10000,
						3,
						0
					],
					[
						10185.1851851852,
						0,
						0
					],
					[
						9722.22222222222,
						1,
						0
					],
					[
						9814.81481481481,
						2,
						0
					],
					[
						9907.40740740741,
						0,
						0
					],
					[
						10185.1851851852,
						2,
						0
					]
				],
				"altAnim": false,
				"gfSection": false,
				"bpm": 165,
				"changeBPM": false,
				"mustHitSection": true
			},
			{
				"lengthInSteps": 16,
				"typeOfSection": 0,
				"sectionNotes": [
					[
						10370.3703703704,
						0,
						0
					],
					[
						10555.5555555556,
						1,
						0
					],
					[
						10740.7407407407,
						2,
						0
					],
					[
						10925.9259259259,
						0,
						0
					],
					[
						11111.1111111111,
						3,
						0
					],
					[
						11296.2962962963,
						2,
						0
					],
					[
						11481.4814814815,
						1,
						0
					],
					[
						11574.0740740741,
						2,
						0
					],
					[
						11666.6666666667,
						3,
						0
					]
				],
				"altAnim": false,
				"gfSection": false,
				"bpm": 165,
				"changeBPM": false,
				"mustHitSection": true
			},
			{
				"lengthInSteps": 16,
				"typeOfSection": 0,
				"sectionNotes": [],
				"altAnim": false,
				"gfSection": false,
				"bpm": 165,
				"changeBPM": false,
				"mustHitSection": true
			},
			{
				"lengthInSteps": 16,
				"typeOfSection": 0,
				"sectionNotes": [],
				"altAnim": false,
				"gfSection": false,
				"bpm": 165,
				"changeBPM": false,
				"mustHitSection": true
			},
			{
				"lengthInSteps": 16,
				"typeOfSection": 0,
				"sectionNotes": [
					[
						14814.8148148148,
						0,
						0
					],
					[
						14907.4074074074,
						1,
						0
					],
					[
						15000,
						2,
						0
					],
					[
						15092.5925925926,
						0,
						0
					],
					[
						15185.1851851852,
						1,
						0
					],
					[
						15277.7777777778,
						3,
						0
					],
					[
						15370.3703703704,
						2,
						0
					],
					[
						15462.962962963,
						0,
						0
					],
					[
						15555.5555555556,
						1,
						0
					],
					[
						15740.7407407407,
						2,
						0
					],
					[
						15925.9259259259,
						0,
						0
					],
					[
						16111.1111111111,
						2,
						0
					]
				],
				"altAnim": false,
				"gfSection": false,
				"bpm": 165,
				"changeBPM": false,
				"mustHitSection": false
			},
			{
				"lengthInSteps": 16,
				"typeOfSection": 0,
				"sectionNotes": [
					[
						16296.2962962963,
						0,
						0
					],
					[
						16481.4814814815,
						3,
						0
					],
					[
						16666.6666666667,
						2,
						0
					],
					[
						16851.8518518519,
						0,
						0
					],
					[
						16944.4444444444,
						1,
						0
					],
					[
						17037.037037037,
						3,
						0
					],
					[
						17129.6296296296,
						2,
						0
					],
					[
						17222.2222222222,
						0,
						0
					],
					[
						17314.8148148148,
						1,
						0
					],
					[
						17407.4074074074,
						3,
						0
					],
					[
						17592.5925925926,
						1,
						0
					]
				],
				"altAnim": false,
				"gfSection": false,
				"bpm": 165,
				"changeBPM": false,
				"mustHitSection": false
			},
			{
				"lengthInSteps": 16,
				"typeOfSection": 0,
				"sectionNotes": [
					[
						17777.7777777778,
						0,
						0
					],
					[
						17870.3703703704,
						1,
						0
					],
					[
						17962.962962963,
						2,
						0
					],
					[
						18055.5555555556,
						0,
						0
					],
					[
						18148.1481481481,
						1,
						0
					],
					[
						18240.7407407407,
						3,
						0
					],
					[
						18333.3333333333,
						2,
						0
					],
					[
						18425.9259259259,
						0,
						0
					],
					[
						18518.5185185185,
						1,
						0
					],
					[
						18703.7037037037,
						2,
						0
					],
					[
						19074.0740740741,
						2,
						0
					],
					[
						18888.8888888889,
						0,
						0
					]
				],
				"altAnim": false,
				"gfSection": false,
				"bpm": 165,
				"changeBPM": false,
				"mustHitSection": true
			},
			{
				"lengthInSteps": 16,
				"typeOfSection": 0,
				"sectionNotes": [
					[
						19259.2592592593,
						0,
						0
					],
					[
						19444.4444444444,
						3,
						0
					],
					[
						19629.6296296296,
						2,
						0
					],
					[
						19814.8148148148,
						0,
						0
					],
					[
						19907.4074074074,
						1,
						0
					],
					[
						20000,
						3,
						0
					],
					[
						20092.5925925926,
						2,
						0
					],
					[
						20185.1851851852,
						0,
						0
					],
					[
						20277.7777777778,
						1,
						0
					],
					[
						20370.3703703704,
						3,
						0
					],
					[
						20555.5555555556,
						1,
						0
					]
				],
				"altAnim": false,
				"gfSection": false,
				"bpm": 165,
				"changeBPM": false,
				"mustHitSection": true
			},
			{
				"lengthInSteps": 16,
				"typeOfSection": 0,
				"sectionNotes": [
					[
						20740.7407407407,
						0,
						0
					],
					[
						20833.3333333333,
						1,
						0
					],
					[
						20925.9259259259,
						2,
						0
					],
					[
						21018.5185185185,
						0,
						0
					],
					[
						21111.1111111111,
						1,
						0
					],
					[
						21203.7037037037,
						3,
						0
					],
					[
						21296.2962962963,
						2,
						0
					],
					[
						21388.8888888889,
						0,
						0
					],
					[
						21481.4814814815,
						1,
						0
					],
					[
						21666.6666666667,
						2,
						0
					],
					[
						21851.8518518519,
						0,
						0
					],
					[
						22037.037037037,
						2,
						0
					]
				],
				"altAnim": false,
				"gfSection": false,
				"bpm": 165,
				"changeBPM": false,
				"mustHitSection": false
			},
			{
				"lengthInSteps": 16,
				"typeOfSection": 0,
				"sectionNotes": [
					[
						22222.2222222222,
						0,
						0
					],
					[
						22407.4074074074,
						3,
						0
					],
					[
						22592.5925925926,
						2,
						0
					],
					[
						22777.7777777778,
						0,
						0
					],
					[
						22870.3703703704,
						1,
						0
					],
					[
						22962.962962963,
						3,
						0
					],
					[
						23055.5555555556,
						2,
						0
					],
					[
						23148.1481481481,
						0,
						0
					],
					[
						23240.7407407407,
						1,
						0
					],
					[
						23333.3333333333,
						3,
						0
					],
					[
						23518.5185185185,
						1,
						0
					]
				],
				"altAnim": false,
				"gfSection": false,
				"bpm": 165,
				"changeBPM": false,
				"mustHitSection": false
			},
			{
				"lengthInSteps": 16,
				"typeOfSection": 0,
				"sectionNotes": [
					[
						23703.7037037037,
						0,
						0
					],
					[
						23796.2962962963,
						1,
						0
					],
					[
						23888.8888888889,
						2,
						0
					],
					[
						23981.4814814815,
						0,
						0
					],
					[
						24074.0740740741,
						1,
						0
					],
					[
						24166.6666666667,
						3,
						0
					],
					[
						24259.2592592593,
						2,
						0
					],
					[
						24351.8518518519,
						0,
						0
					],
					[
						24444.4444444444,
						1,
						0
					],
					[
						24629.6296296296,
						2,
						0
					],
					[
						24814.8148148148,
						0,
						0
					],
					[
						25000,
						2,
						0
					]
				],
				"altAnim": false,
				"gfSection": false,
				"bpm": 165,
				"changeBPM": false,
				"mustHitSection": true
			},
			{
				"lengthInSteps": 16,
				"typeOfSection": 0,
				"sectionNotes": [
					[
						25185.1851851852,
						0,
						0
					],
					[
						25370.3703703704,
						3,
						0
					],
					[
						25555.5555555556,
						2,
						0
					],
					[
						25740.7407407407,
						0,
						0
					],
					[
						25833.3333333333,
						1,
						0
					],
					[
						25925.9259259259,
						3,
						0
					],
					[
						26018.5185185185,
						2,
						0
					],
					[
						26111.1111111111,
						0,
						0
					],
					[
						26203.7037037037,
						1,
						0
					],
					[
						26296.2962962963,
						3,
						0
					],
					[
						26481.4814814815,
						1,
						0
					]
				],
				"altAnim": false,
				"gfSection": false,
				"bpm": 165,
				"changeBPM": false,
				"mustHitSection": true
			},
			{
				"lengthInSteps": 16,
				"typeOfSection": 0,
				"sectionNotes": [
					[
						26666.6666666667,
						0,
						0
					],
					[
						26851.8518518519,
						1,
						0
					],
					[
						26944.4444444444,
						2,
						0
					],
					[
						27037.037037037,
						3,
						0
					],
					[
						27222.2222222222,
						1,
						0
					],
					[
						27407.4074074074,
						0,
						0
					],
					[
						27592.5925925926,
						1,
						0
					],
					[
						27685.1851851852,
						2,
						0
					],
					[
						27777.7777777778,
						1,
						0
					],
					[
						27870.3703703704,
						2,
						0
					],
					[
						27962.962962963,
						0,
						0
					],
					[
						28055.5555555556,
						3,
						0
					]
				],
				"altAnim": false,
				"gfSection": false,
				"bpm": 165,
				"changeBPM": false,
				"mustHitSection": false
			},
			{
				"lengthInSteps": 16,
				"typeOfSection": 0,
				"sectionNotes": [
					[
						28333.3333333333,
						1,
						0
					],
					[
						28425.9259259259,
						2,
						0
					],
					[
						28148.1481481481,
						3,
						0
					],
					[
						28518.5185185185,
						0,
						0
					],
					[
						28703.7037037037,
						1,
						0
					],
					[
						28888.8888888889,
						2,
						0
					],
					[
						28981.4814814815,
						3,
						0
					],
					[
						29074.0740740741,
						2,
						0
					],
					[
						29259.2592592593,
						0,
						0
					],
					[
						29351.8518518519,
						1,
						0
					],
					[
						29444.4444444444,
						3,
						0
					]
				],
				"altAnim": false,
				"gfSection": false,
				"bpm": 165,
				"changeBPM": false,
				"mustHitSection": false
			},
			{
				"lengthInSteps": 16,
				"typeOfSection": 0,
				"sectionNotes": [
					[
						29629.6296296296,
						0,
						0
					],
					[
						29814.8148148148,
						1,
						0
					],
					[
						29907.4074074074,
						2,
						0
					],
					[
						30000,
						3,
						0
					],
					[
						30185.1851851852,
						1,
						0
					],
					[
						30370.3703703704,
						0,
						0
					],
					[
						30555.5555555556,
						1,
						0
					],
					[
						30648.1481481481,
						2,
						0
					],
					[
						30740.7407407407,
						1,
						0
					],
					[
						30833.3333333333,
						2,
						0
					],
					[
						30925.9259259259,
						0,
						0
					],
					[
						31018.5185185185,
						3,
						0
					]
				],
				"altAnim": false,
				"gfSection": false,
				"bpm": 165,
				"changeBPM": false,
				"mustHitSection": true
			},
			{
				"lengthInSteps": 16,
				"typeOfSection": 0,
				"sectionNotes": [
					[
						31296.2962962963,
						1,
						0
					],
					[
						31388.8888888889,
						2,
						0
					],
					[
						31111.1111111111,
						3,
						0
					],
					[
						31481.4814814815,
						0,
						0
					],
					[
						31666.6666666667,
						1,
						0
					],
					[
						31851.8518518519,
						2,
						0
					],
					[
						31944.4444444444,
						3,
						0
					],
					[
						32037.037037037,
						2,
						0
					],
					[
						32222.2222222222,
						0,
						0
					],
					[
						32314.8148148148,
						1,
						0
					],
					[
						32407.4074074074,
						3,
						0
					]
				],
				"altAnim": false,
				"gfSection": false,
				"bpm": 165,
				"changeBPM": false,
				"mustHitSection": true
			},
			{
				"lengthInSteps": 16,
				"typeOfSection": 0,
				"sectionNotes": [
					[
						32592.5925925926,
						0,
						0
					],
					[
						32592.5925925926,
						4,
						0
					],
					[
						32777.7777777778,
						1,
						0
					],
					[
						32777.7777777778,
						5,
						0
					],
					[
						32962.962962963,
						7,
						0
					],
					[
						32962.962962963,
						3,
						0
					],
					[
						33148.1481481482,
						0,
						0
					],
					[
						33148.1481481482,
						4,
						0
					],
					[
						33333.3333333333,
						7,
						0
					],
					[
						33333.3333333333,
						3,
						0
					],
					[
						33518.5185185185,
						2,
						0
					],
					[
						33518.5185185185,
						6,
						0
					],
					[
						33703.7037037037,
						0,
						0
					],
					[
						33703.7037037037,
						4,
						0
					],
					[
						33796.2962962963,
						7,
						0
					],
					[
						33796.2962962963,
						3,
						0
					],
					[
						33888.8888888889,
						0,
						0
					],
					[
						33888.8888888889,
						4,
						0
					]
				],
				"altAnim": false,
				"gfSection": false,
				"bpm": 165,
				"changeBPM": false,
				"mustHitSection": true
			},
			{
				"lengthInSteps": 16,
				"typeOfSection": 0,
				"sectionNotes": [
					[
						34074.0740740741,
						0,
						0
					],
					[
						34166.6666666667,
						1,
						0
					],
					[
						34259.2592592593,
						2,
						0
					],
					[
						34074.0740740741,
						4,
						0
					],
					[
						34166.6666666667,
						5,
						0
					],
					[
						34259.2592592593,
						6,
						0
					],
					[
						34351.8518518519,
						3,
						0
					],
					[
						34351.8518518519,
						7,
						0
					],
					[
						34444.4444444444,
						6,
						0
					],
					[
						34537.037037037,
						5,
						0
					],
					[
						34629.6296296296,
						4,
						0
					],
					[
						34444.4444444444,
						2,
						0
					],
					[
						34537.037037037,
						1,
						0
					],
					[
						34629.6296296296,
						0,
						0
					],
					[
						34722.2222222222,
						1,
						0
					],
					[
						34722.2222222222,
						5,
						0
					],
					[
						34814.8148148148,
						3,
						185.185185185185
					],
					[
						34814.8148148148,
						7,
						185.185185185185
					],
					[
						35092.5925925926,
						0,
						0
					],
					[
						35092.5925925926,
						4,
						0
					],
					[
						35185.1851851852,
						1,
						0
					],
					[
						35185.1851851852,
						5,
						0
					],
					[
						35370.3703703704,
						3,
						0
					],
					[
						35370.3703703704,
						7,
						0
					]
				],
				"altAnim": false,
				"gfSection": false,
				"bpm": 165,
				"changeBPM": false,
				"mustHitSection": false
			},
			{
				"lengthInSteps": 16,
				"typeOfSection": 0,
				"sectionNotes": [
					[
						35555.5555555556,
						0,
						0
					],
					[
						35555.5555555556,
						4,
						0
					],
					[
						35740.7407407407,
						1,
						0
					],
					[
						35740.7407407407,
						5,
						0
					],
					[
						35925.9259259259,
						6,
						0
					],
					[
						36111.1111111111,
						3,
						0
					],
					[
						36111.1111111111,
						7,
						0
					],
					[
						36296.2962962963,
						0,
						0
					],
					[
						36481.4814814815,
						1,
						0
					],
					[
						36666.6666666667,
						2,
						0
					],
					[
						36851.8518518519,
						3,
						0
					],
					[
						36296.2962962963,
						4,
						0
					],
					[
						36481.4814814815,
						5,
						0
					],
					[
						36666.6666666667,
						6,
						0
					],
					[
						36851.8518518519,
						7,
						0
					],
					[
						35925.9259259259,
						0,
						0
					],
					[
						35925.9259259259,
						4,
						0
					],
					[
						36481.4814814815,
						7,
						0
					],
					[
						36481.4814814815,
						3,
						0
					],
					[
						36759.2592592593,
						1,
						0
					],
					[
						36759.2592592593,
						5,
						0
					],
					[
						35925.9259259259,
						2,
						0
					]
				],
				"altAnim": false,
				"gfSection": false,
				"bpm": 165,
				"changeBPM": false,
				"mustHitSection": true
			},
			{
				"lengthInSteps": 16,
				"typeOfSection": 0,
				"sectionNotes": [
					[
						37037.037037037,
						0,
						0
					],
					[
						37129.6296296296,
						1,
						0
					],
					[
						37037.037037037,
						4,
						0
					],
					[
						37129.6296296296,
						5,
						0
					],
					[
						37407.4074074074,
						0,
						0
					],
					[
						37407.4074074074,
						4,
						0
					],
					[
						37592.5925925926,
						1,
						0
					],
					[
						37592.5925925926,
						5,
						0
					],
					[
						37777.7777777778,
						7,
						0
					],
					[
						37777.7777777778,
						3,
						0
					],
					[
						37962.962962963,
						0,
						0
					],
					[
						37962.962962963,
						4,
						0
					],
					[
						38055.5555555556,
						1,
						0
					],
					[
						38148.1481481481,
						2,
						0
					],
					[
						38055.5555555556,
						5,
						0
					],
					[
						38148.1481481481,
						6,
						0
					],
					[
						38333.3333333333,
						7,
						0
					],
					[
						38333.3333333333,
						3,
						0
					],
					[
						37222.2222222222,
						6,
						0
					],
					[
						37222.2222222222,
						2,
						0
					]
				],
				"altAnim": false,
				"gfSection": false,
				"bpm": 165,
				"changeBPM": false,
				"mustHitSection": false
			},
			{
				"lengthInSteps": 16,
				"typeOfSection": 0,
				"sectionNotes": [
					[
						38518.5185185185,
						0,
						0
					],
					[
						39259.2592592593,
						1,
						0
					],
					[
						39351.8518518519,
						2,
						0
					],
					[
						39444.4444444444,
						0,
						0
					],
					[
						39537.037037037,
						1,
						0
					],
					[
						39629.6296296296,
						3,
						0
					],
					[
						39814.8148148148,
						0,
						0
					],
					[
						39074.0740740741,
						3,
						0
					],
					[
						38703.7037037037,
						2,
						0
					],
					[
						38888.8888888889,
						1,
						0
					]
				],
				"altAnim": false,
				"gfSection": false,
				"bpm": 165,
				"changeBPM": false,
				"mustHitSection": false
			},
			{
				"lengthInSteps": 16,
				"typeOfSection": 0,
				"sectionNotes": [
					[
						40000,
						0,
						0
					],
					[
						40185.1851851852,
						1,
						0
					],
					[
						40277.7777777778,
						2,
						0
					],
					[
						40370.3703703704,
						3,
						0
					],
					[
						40462.962962963,
						2,
						0
					],
					[
						40555.5555555556,
						1,
						0
					],
					[
						40740.7407407407,
						2,
						0
					],
					[
						40925.9259259259,
						0,
						0
					],
					[
						41111.1111111111,
						1,
						0
					],
					[
						41296.2962962963,
						1,
						0
					]
				],
				"altAnim": false,
				"gfSection": false,
				"bpm": 165,
				"changeBPM": false,
				"mustHitSection": false
			},
			{
				"lengthInSteps": 16,
				"typeOfSection": 0,
				"sectionNotes": [
					[
						41481.4814814815,
						0,
						0
					],
					[
						42222.2222222222,
						1,
						0
					],
					[
						42314.8148148148,
						2,
						0
					],
					[
						42407.4074074074,
						0,
						0
					],
					[
						42500,
						1,
						0
					],
					[
						42592.5925925926,
						3,
						0
					],
					[
						42777.7777777778,
						0,
						0
					],
					[
						42037.037037037,
						3,
						0
					],
					[
						41666.6666666667,
						2,
						0
					],
					[
						41851.8518518519,
						1,
						0
					]
				],
				"altAnim": false,
				"gfSection": false,
				"bpm": 165,
				"changeBPM": false,
				"mustHitSection": true
			},
			{
				"lengthInSteps": 16,
				"typeOfSection": 0,
				"sectionNotes": [
					[
						42962.962962963,
						0,
						0
					],
					[
						43148.1481481481,
						1,
						0
					],
					[
						43240.7407407407,
						2,
						0
					],
					[
						43333.3333333333,
						3,
						0
					],
					[
						43425.9259259259,
						2,
						0
					],
					[
						43518.5185185185,
						1,
						0
					],
					[
						43703.7037037037,
						2,
						0
					],
					[
						43888.8888888889,
						0,
						0
					],
					[
						44074.0740740741,
						1,
						0
					],
					[
						44259.2592592593,
						1,
						0
					]
				],
				"altAnim": false,
				"gfSection": false,
				"bpm": 165,
				"changeBPM": false,
				"mustHitSection": true
			},
			{
				"lengthInSteps": 16,
				"typeOfSection": 0,
				"sectionNotes": [
					[
						44444.4444444444,
						0,
						0
					],
					[
						44629.6296296296,
						1,
						0
					],
					[
						44814.8148148148,
						2,
						0
					],
					[
						45000,
						0,
						0
					],
					[
						45185.1851851852,
						3,
						0
					],
					[
						45370.3703703704,
						1,
						0
					],
					[
						45555.5555555556,
						2,
						0
					],
					[
						45740.7407407407,
						0,
						0
					],
					[
						45833.3333333333,
						1,
						0
					]
				],
				"altAnim": false,
				"gfSection": false,
				"bpm": 165,
				"changeBPM": false,
				"mustHitSection": false
			},
			{
				"lengthInSteps": 16,
				"typeOfSection": 0,
				"sectionNotes": [
					[
						45925.9259259259,
						3,
						0
					],
					[
						46018.5185185185,
						2,
						0
					],
					[
						46111.1111111111,
						3,
						0
					],
					[
						46388.8888888889,
						1,
						0
					],
					[
						46481.4814814815,
						0,
						0
					],
					[
						46666.6666666667,
						3,
						0
					],
					[
						46759.2592592593,
						2,
						0
					],
					[
						46851.8518518519,
						3,
						0
					],
					[
						46296.2962962963,
						1,
						0
					],
					[
						46203.7037037037,
						2,
						0
					],
					[
						46574.0740740741,
						1,
						0
					],
					[
						46944.4444444444,
						0,
						0
					],
					[
						47037.037037037,
						1,
						0
					],
					[
						47129.6296296296,
						0,
						0
					],
					[
						47222.2222222222,
						3,
						0
					]
				],
				"altAnim": false,
				"gfSection": false,
				"bpm": 165,
				"changeBPM": false,
				"mustHitSection": false
			},
			{
				"lengthInSteps": 16,
				"typeOfSection": 0,
				"sectionNotes": [
					[
						47407.4074074074,
						0,
						0
					],
					[
						47777.7777777778,
						1,
						0
					],
					[
						47592.5925925926,
						2,
						0
					],
					[
						47962.962962963,
						0,
						0
					],
					[
						48148.1481481481,
						3,
						0
					],
					[
						48333.3333333333,
						2,
						0
					],
					[
						48518.5185185185,
						3,
						0
					],
					[
						48703.7037037037,
						0,
						0
					],
					[
						48703.7037037037,
						4,
						0,
						"Warning Note"
					]
				],
				"altAnim": false,
				"gfSection": false,
				"bpm": 165,
				"changeBPM": false,
				"mustHitSection": false
			},
			{
				"lengthInSteps": 16,
				"typeOfSection": 0,
				"sectionNotes": [
					[
						48888.8888888889,
						2,
						0
					],
					[
						49074.0740740741,
						1,
						0
					],
					[
						49259.2592592593,
						3,
						0
					],
					[
						49444.4444444444,
						1,
						0
					],
					[
						49629.6296296296,
						0,
						0
					],
					[
						49814.8148148148,
						1,
						0
					],
					[
						50000,
						2,
						0
					],
					[
						50185.1851851852,
						3,
						0
					],
					[
						50000,
						7,
						0,
						"Warning Note"
					]
				],
				"altAnim": false,
				"gfSection": false,
				"bpm": 165,
				"changeBPM": false,
				"mustHitSection": false
			},
			{
				"lengthInSteps": 16,
				"typeOfSection": 0,
				"sectionNotes": [
					[
						50370.3703703704,
						0,
						0
					],
					[
						50555.5555555556,
						1,
						0
					],
					[
						50740.7407407407,
						2,
						0
					],
					[
						50925.9259259259,
						0,
						0
					],
					[
						51111.1111111111,
						3,
						0
					],
					[
						51296.2962962963,
						1,
						0
					],
					[
						51481.4814814815,
						2,
						0
					],
					[
						51666.6666666667,
						0,
						0
					],
					[
						51759.2592592593,
						1,
						0
					]
				],
				"altAnim": false,
				"gfSection": false,
				"bpm": 165,
				"changeBPM": false,
				"mustHitSection": true
			},
			{
				"lengthInSteps": 16,
				"typeOfSection": 0,
				"sectionNotes": [
					[
						51851.8518518519,
						3,
						0
					],
					[
						51944.4444444444,
						2,
						0
					],
					[
						52037.037037037,
						3,
						0
					],
					[
						52314.8148148148,
						1,
						0
					],
					[
						52407.4074074074,
						0,
						0
					],
					[
						52592.5925925926,
						3,
						0
					],
					[
						52685.1851851852,
						2,
						0
					],
					[
						52777.7777777778,
						3,
						0
					],
					[
						52222.2222222222,
						1,
						0
					],
					[
						52129.6296296296,
						2,
						0
					],
					[
						52500,
						1,
						0
					],
					[
						52870.3703703704,
						0,
						0
					],
					[
						52962.962962963,
						1,
						0
					],
					[
						53055.5555555556,
						0,
						0
					],
					[
						53148.1481481482,
						3,
						0
					]
				],
				"altAnim": false,
				"gfSection": false,
				"bpm": 165,
				"changeBPM": false,
				"mustHitSection": true
			},
			{
				"lengthInSteps": 16,
				"typeOfSection": 0,
				"sectionNotes": [
					[
						53333.3333333333,
						0,
						0
					],
					[
						53703.7037037037,
						1,
						0
					],
					[
						53518.5185185185,
						2,
						0
					],
					[
						53888.8888888889,
						0,
						0
					],
					[
						54074.0740740741,
						3,
						0
					],
					[
						54259.2592592593,
						2,
						0
					],
					[
						54444.4444444444,
						3,
						0
					],
					[
						54629.6296296296,
						0,
						0
					]
				],
				"altAnim": false,
				"gfSection": false,
				"bpm": 165,
				"changeBPM": false,
				"mustHitSection": true
			},
			{
				"lengthInSteps": 16,
				"typeOfSection": 0,
				"sectionNotes": [
					[
						54814.8148148148,
						2,
						0
					],
					[
						55000,
						1,
						0
					],
					[
						55185.1851851852,
						3,
						0
					],
					[
						55370.3703703704,
						1,
						0
					],
					[
						55555.5555555556,
						0,
						0
					],
					[
						55740.7407407407,
						1,
						0
					],
					[
						55925.9259259259,
						2,
						0
					],
					[
						56111.1111111111,
						3,
						0
					]
				],
				"altAnim": false,
				"gfSection": false,
				"bpm": 165,
				"changeBPM": false,
				"mustHitSection": true
			},
			{
				"lengthInSteps": 16,
				"typeOfSection": 0,
				"sectionNotes": [
					[
						56296.2962962963,
						0,
						0
					],
					[
						56388.8888888889,
						1,
						0
					],
					[
						56481.4814814815,
						3,
						0
					],
					[
						56666.6666666667,
						1,
						0
					],
					[
						56759.2592592593,
						2,
						0
					],
					[
						56851.8518518519,
						3,
						0
					],
					[
						56944.4444444444,
						0,
						0
					],
					[
						57037.037037037,
						2,
						0
					],
					[
						57222.2222222222,
						1,
						0
					],
					[
						57314.8148148148,
						2,
						0
					],
					[
						57407.4074074074,
						3,
						0
					],
					[
						57592.5925925926,
						0,
						0
					],
					[
						57685.1851851852,
						1,
						0
					]
				],
				"altAnim": false,
				"gfSection": false,
				"bpm": 165,
				"changeBPM": false,
				"mustHitSection": false
			},
			{
				"lengthInSteps": 16,
				"typeOfSection": 0,
				"sectionNotes": [
					[
						57777.7777777778,
						3,
						0
					],
					[
						57870.3703703704,
						2,
						0
					],
					[
						57962.962962963,
						0,
						0
					],
					[
						58148.1481481482,
						1,
						0
					],
					[
						58333.3333333333,
						3,
						0
					],
					[
						58518.5185185185,
						1,
						0
					],
					[
						58703.7037037037,
						2,
						0
					],
					[
						58888.8888888889,
						0,
						0
					],
					[
						59074.0740740741,
						0,
						0
					]
				],
				"altAnim": false,
				"gfSection": false,
				"bpm": 165,
				"changeBPM": false,
				"mustHitSection": false
			},
			{
				"lengthInSteps": 16,
				"typeOfSection": 0,
				"sectionNotes": [
					[
						59259.2592592593,
						0,
						0
					],
					[
						59351.8518518519,
						1,
						0
					],
					[
						59444.4444444444,
						3,
						0
					],
					[
						59629.6296296296,
						1,
						0
					],
					[
						59722.2222222222,
						2,
						0
					],
					[
						59814.8148148148,
						3,
						0
					],
					[
						59907.4074074074,
						0,
						0
					],
					[
						60000,
						2,
						0
					],
					[
						60185.1851851852,
						1,
						0
					],
					[
						60277.7777777778,
						2,
						0
					],
					[
						60370.3703703704,
						3,
						0
					],
					[
						60555.5555555556,
						0,
						0
					],
					[
						60648.1481481482,
						1,
						0
					]
				],
				"altAnim": false,
				"gfSection": false,
				"bpm": 165,
				"changeBPM": false,
				"mustHitSection": true
			},
			{
				"lengthInSteps": 16,
				"typeOfSection": 0,
				"sectionNotes": [
					[
						60740.7407407407,
						3,
						0
					],
					[
						60833.3333333333,
						2,
						0
					],
					[
						60925.9259259259,
						0,
						0
					],
					[
						61111.1111111111,
						1,
						0
					],
					[
						61296.2962962963,
						3,
						0
					],
					[
						61481.4814814815,
						1,
						0
					],
					[
						61666.6666666667,
						2,
						0
					],
					[
						61851.8518518519,
						0,
						0
					],
					[
						62037.037037037,
						0,
						0
					]
				],
				"altAnim": false,
				"gfSection": false,
				"bpm": 165,
				"changeBPM": false,
				"mustHitSection": true
			},
			{
				"lengthInSteps": 16,
				"typeOfSection": 0,
				"sectionNotes": [
					[
						62222.2222222222,
						0,
						0
					],
					[
						62314.8148148148,
						1,
						0
					],
					[
						62500,
						3,
						0
					],
					[
						62407.4074074074,
						2,
						0
					],
					[
						62592.5925925926,
						0,
						0
					],
					[
						62685.1851851852,
						1,
						0
					],
					[
						62777.7777777778,
						0,
						0
					],
					[
						62870.3703703704,
						2,
						0
					],
					[
						62962.962962963,
						3,
						0
					],
					[
						63148.1481481482,
						1,
						0
					],
					[
						63333.3333333333,
						2,
						0
					],
					[
						63518.5185185185,
						0,
						0
					]
				],
				"altAnim": false,
				"gfSection": false,
				"bpm": 165,
				"changeBPM": false,
				"mustHitSection": false
			},
			{
				"lengthInSteps": 16,
				"typeOfSection": 0,
				"sectionNotes": [
					[
						63703.7037037037,
						3,
						0
					],
					[
						63888.8888888889,
						2,
						0
					],
					[
						64074.0740740741,
						0,
						0
					],
					[
						64351.8518518519,
						2,
						0
					],
					[
						64259.2592592593,
						1,
						0
					],
					[
						64444.4444444444,
						3,
						0
					],
					[
						64537.037037037,
						2,
						0
					],
					[
						64722.2222222222,
						0,
						0
					],
					[
						64629.6296296296,
						1,
						0
					],
					[
						64814.8148148148,
						3,
						0
					],
					[
						65000,
						2,
						0
					]
				],
				"altAnim": false,
				"gfSection": false,
				"bpm": 165,
				"changeBPM": false,
				"mustHitSection": false
			},
			{
				"lengthInSteps": 16,
				"typeOfSection": 0,
				"sectionNotes": [
					[
						65185.1851851852,
						0,
						0
					],
					[
						65277.7777777778,
						1,
						0
					],
					[
						65462.962962963,
						3,
						0
					],
					[
						65370.3703703704,
						2,
						0
					],
					[
						65555.5555555556,
						0,
						0
					],
					[
						65648.1481481481,
						1,
						0
					],
					[
						65740.7407407407,
						0,
						0
					],
					[
						65833.3333333333,
						2,
						0
					],
					[
						65925.9259259259,
						3,
						0
					],
					[
						66111.1111111111,
						1,
						0
					],
					[
						66296.2962962963,
						2,
						0
					],
					[
						66481.4814814815,
						0,
						0
					]
				],
				"altAnim": false,
				"gfSection": false,
				"bpm": 165,
				"changeBPM": false,
				"mustHitSection": true
			},
			{
				"lengthInSteps": 16,
				"typeOfSection": 0,
				"sectionNotes": [
					[
						66666.6666666667,
						3,
						0
					],
					[
						66851.8518518519,
						2,
						0
					],
					[
						67037.037037037,
						0,
						0
					],
					[
						67314.8148148148,
						2,
						0
					],
					[
						67222.2222222222,
						1,
						0
					],
					[
						67407.4074074074,
						3,
						0
					],
					[
						67500,
						2,
						0
					],
					[
						67685.1851851852,
						0,
						0
					],
					[
						67592.5925925926,
						1,
						0
					],
					[
						67777.7777777778,
						3,
						0
					],
					[
						67962.962962963,
						2,
						0
					]
				],
				"altAnim": false,
				"gfSection": false,
				"bpm": 165,
				"changeBPM": false,
				"mustHitSection": true
			},
			{
				"lengthInSteps": 16,
				"typeOfSection": 0,
				"sectionNotes": [
					[
						68148.1481481481,
						0,
						0
					],
					[
						68240.7407407407,
						1,
						0
					],
					[
						68333.3333333333,
						0,
						0
					],
					[
						68425.9259259259,
						2,
						0
					],
					[
						68518.5185185185,
						3,
						0
					],
					[
						68611.1111111111,
						2,
						0
					],
					[
						68796.2962962963,
						3,
						0
					],
					[
						68981.4814814815,
						1,
						0
					],
					[
						69074.0740740741,
						2,
						0
					],
					[
						69166.6666666667,
						0,
						0
					],
					[
						69351.8518518519,
						1,
						0
					],
					[
						69444.4444444444,
						2,
						0
					],
					[
						69537.037037037,
						3,
						0
					]
				],
				"altAnim": false,
				"gfSection": false,
				"bpm": 165,
				"changeBPM": false,
				"mustHitSection": false
			},
			{
				"lengthInSteps": 16,
				"typeOfSection": 0,
				"sectionNotes": [
					[
						69629.6296296296,
						0,
						0
					],
					[
						69722.2222222222,
						1,
						0
					],
					[
						69814.8148148148,
						3,
						0
					],
					[
						70000,
						2,
						0
					],
					[
						70185.1851851852,
						0,
						0
					],
					[
						70370.3703703704,
						1,
						0
					],
					[
						70462.9629629629,
						2,
						0
					],
					[
						70555.5555555555,
						3,
						0
					],
					[
						70740.7407407407,
						1,
						0
					],
					[
						70648.1481481481,
						2,
						0
					],
					[
						70925.9259259259,
						2,
						0
					],
					[
						70833.3333333333,
						2,
						0
					],
					[
						71018.5185185185,
						0,
						0
					]
				],
				"altAnim": false,
				"gfSection": false,
				"bpm": 165,
				"changeBPM": false,
				"mustHitSection": false
			},
			{
				"lengthInSteps": 16,
				"typeOfSection": 0,
				"sectionNotes": [
					[
						71111.1111111111,
						0,
						0
					],
					[
						71203.7037037037,
						1,
						0
					],
					[
						71296.2962962963,
						0,
						0
					],
					[
						71388.8888888889,
						2,
						0
					],
					[
						71481.4814814815,
						3,
						0
					],
					[
						71574.0740740741,
						2,
						0
					],
					[
						71759.2592592593,
						3,
						0
					],
					[
						71944.4444444444,
						1,
						0
					],
					[
						72037.037037037,
						2,
						0
					],
					[
						72129.6296296296,
						0,
						0
					],
					[
						72314.8148148148,
						1,
						0
					],
					[
						72407.4074074074,
						2,
						0
					],
					[
						72500,
						3,
						0
					]
				],
				"altAnim": false,
				"gfSection": false,
				"bpm": 165,
				"changeBPM": false,
				"mustHitSection": true
			},
			{
				"lengthInSteps": 16,
				"typeOfSection": 0,
				"sectionNotes": [
					[
						72592.5925925926,
						0,
						0
					],
					[
						72685.1851851852,
						1,
						0
					],
					[
						72777.7777777778,
						3,
						0
					],
					[
						72962.9629629629,
						2,
						0
					],
					[
						73148.1481481481,
						0,
						0
					],
					[
						73333.3333333333,
						1,
						0
					],
					[
						73425.9259259259,
						2,
						0
					],
					[
						73518.5185185185,
						3,
						0
					],
					[
						73703.7037037037,
						1,
						0
					],
					[
						73611.1111111111,
						2,
						0
					],
					[
						73888.8888888889,
						2,
						0
					],
					[
						73796.2962962963,
						2,
						0
					],
					[
						73981.4814814815,
						0,
						0
					]
				],
				"altAnim": false,
				"gfSection": false,
				"bpm": 165,
				"changeBPM": false,
				"mustHitSection": false
			},
			{
				"lengthInSteps": 16,
				"typeOfSection": 0,
				"sectionNotes": [
					[
						74074.074074074,
						6,
						462.962962962963
					],
					[
						74074.074074074,
						0,
						0
					],
					[
						74166.6666666666,
						1,
						0
					],
					[
						74259.2592592592,
						3,
						0
					],
					[
						74629.6296296296,
						3,
						0
					],
					[
						74814.8148148148,
						0,
						0
					],
					[
						74907.4074074074,
						3,
						0
					],
					[
						75185.1851851852,
						2,
						0
					],
					[
						75000,
						0,
						0
					],
					[
						75092.5925925926,
						1,
						0
					],
					[
						75277.7777777778,
						3,
						0
					],
					[
						75370.3703703703,
						1,
						0
					],
					[
						74351.8518518518,
						2,
						0
					],
					[
						74444.4444444444,
						0,
						0
					]
				],
				"altAnim": false,
				"gfSection": false,
				"bpm": 165,
				"changeBPM": false,
				"mustHitSection": false
			},
			{
				"lengthInSteps": 16,
				"typeOfSection": 0,
				"sectionNotes": [
					[
						75555.5555555555,
						0,
						0
					],
					[
						75740.7407407407,
						1,
						0
					],
					[
						75833.3333333333,
						3,
						0
					],
					[
						75925.9259259259,
						2,
						0
					],
					[
						76111.1111111111,
						0,
						0
					],
					[
						76296.2962962963,
						1,
						0
					],
					[
						76388.8888888888,
						2,
						0
					],
					[
						76481.4814814814,
						3,
						0
					],
					[
						76574.074074074,
						3,
						0
					],
					[
						76666.6666666666,
						2,
						0
					],
					[
						76759.2592592592,
						1,
						0
					],
					[
						76851.8518518518,
						0,
						0
					]
				],
				"altAnim": false,
				"gfSection": false,
				"bpm": 165,
				"changeBPM": false,
				"mustHitSection": false
			},
			{
				"lengthInSteps": 16,
				"typeOfSection": 0,
				"sectionNotes": [
					[
						77037.037037037,
						6,
						462.962962962963
					],
					[
						77037.037037037,
						0,
						0
					],
					[
						77129.6296296296,
						1,
						0
					],
					[
						77222.2222222222,
						3,
						0
					],
					[
						77592.5925925926,
						3,
						0
					],
					[
						77777.7777777778,
						0,
						0
					],
					[
						77870.3703703703,
						3,
						0
					],
					[
						78148.1481481481,
						2,
						0
					],
					[
						77962.9629629629,
						0,
						0
					],
					[
						78055.5555555555,
						1,
						0
					],
					[
						78240.7407407407,
						3,
						0
					],
					[
						78333.3333333333,
						1,
						0
					],
					[
						77314.8148148148,
						2,
						0
					],
					[
						77407.4074074074,
						0,
						0
					]
				],
				"altAnim": false,
				"gfSection": false,
				"bpm": 165,
				"changeBPM": false,
				"mustHitSection": true
			},
			{
				"sectionNotes": [
					[
						78518.5185185185,
						0,
						0
					],
					[
						78703.7037037037,
						1,
						0
					],
					[
						78796.2962962963,
						3,
						0
					],
					[
						78888.8888888888,
						2,
						0
					],
					[
						79074.074074074,
						0,
						0
					],
					[
						79259.2592592592,
						1,
						0
					],
					[
						79351.8518518518,
						2,
						0
					],
					[
						79444.4444444444,
						3,
						0
					],
					[
						79537.037037037,
						3,
						0
					],
					[
						79629.6296296296,
						2,
						0
					],
					[
						79722.2222222222,
						1,
						0
					],
					[
						79814.8148148148,
						0,
						0
					]
				],
				"typeOfSection": 0,
				"lengthInSteps": 16,
				"gfSection": false,
				"altAnim": false,
				"mustHitSection": true,
				"changeBPM": false,
				"bpm": 165
			},
			{
				"sectionNotes": [
					[
						79999.9999999999,
						0,
						0
					],
					[
						80092.5925925925,
						1,
						0
					],
					[
						80185.1851851851,
						3,
						0
					],
					[
						80370.3703703703,
						2,
						0
					],
					[
						80462.9629629629,
						0,
						0
					],
					[
						80555.5555555555,
						1,
						0
					],
					[
						80740.7407407407,
						3,
						0
					],
					[
						80833.3333333333,
						2,
						0
					],
					[
						81018.5185185185,
						0,
						0
					],
					[
						81111.1111111111,
						1,
						0
					],
					[
						81203.7037037036,
						2,
						0
					],
					[
						81296.2962962962,
						3,
						0
					],
					[
						79999.9999999999,
						4,
						0
					],
					[
						80092.5925925925,
						5,
						0
					],
					[
						80185.1851851851,
						7,
						0
					],
					[
						80370.3703703703,
						6,
						0
					],
					[
						80462.9629629629,
						4,
						0
					],
					[
						80555.5555555555,
						5,
						0
					],
					[
						80740.7407407407,
						7,
						0
					],
					[
						80833.3333333333,
						6,
						0
					],
					[
						81018.5185185185,
						4,
						0
					],
					[
						81111.1111111111,
						5,
						0
					],
					[
						81203.7037037036,
						6,
						0
					],
					[
						81296.2962962962,
						7,
						0
					],
					[
						80925.9259259259,
						5,
						0
					],
					[
						80925.9259259259,
						1,
						0
					]
				],
				"typeOfSection": 0,
				"lengthInSteps": 16,
				"gfSection": false,
				"altAnim": false,
				"mustHitSection": true,
				"changeBPM": false,
				"bpm": 165
			},
			{
				"sectionNotes": [
					[
						81481.4814814814,
						0,
						0
					],
					[
						81666.6666666666,
						1,
						0
					],
					[
						81481.4814814814,
						4,
						0
					],
					[
						81666.6666666666,
						5,
						0
					],
					[
						81851.8518518518,
						0,
						0
					],
					[
						82037.037037037,
						1,
						0
					],
					[
						81851.8518518518,
						4,
						0
					],
					[
						82037.037037037,
						5,
						0
					],
					[
						82222.2222222222,
						7,
						0
					],
					[
						82222.2222222222,
						3,
						0
					],
					[
						82407.4074074073,
						2,
						0
					],
					[
						82407.4074074073,
						6,
						0
					],
					[
						82592.5925925925,
						0,
						0
					],
					[
						82592.5925925925,
						4,
						0
					],
					[
						82777.7777777777,
						5,
						0
					],
					[
						82777.7777777777,
						1,
						0
					],
					[
						82499.9999999999,
						5,
						0
					],
					[
						82499.9999999999,
						1,
						0
					],
					[
						82685.1851851851,
						7,
						0
					],
					[
						82685.1851851851,
						3,
						0
					],
					[
						82870.3703703703,
						3,
						0
					],
					[
						82870.3703703703,
						7,
						0
					]
				],
				"typeOfSection": 0,
				"lengthInSteps": 16,
				"gfSection": false,
				"altAnim": false,
				"mustHitSection": false,
				"changeBPM": false,
				"bpm": 165
			},
			{
				"sectionNotes": [
					[
						82962.9629629629,
						0,
						0
					],
					[
						83055.5555555555,
						1,
						0
					],
					[
						83148.1481481481,
						3,
						0
					],
					[
						83333.3333333333,
						2,
						0
					],
					[
						83518.5185185185,
						3,
						0
					],
					[
						83703.7037037036,
						2,
						0
					],
					[
						83888.8888888888,
						0,
						0
					],
					[
						84074.074074074,
						1,
						0
					],
					[
						84259.2592592592,
						3,
						0
					],
					[
						82962.9629629629,
						4,
						0
					],
					[
						83055.5555555555,
						5,
						0
					],
					[
						83148.1481481481,
						7,
						0
					],
					[
						83333.3333333333,
						6,
						0
					],
					[
						83518.5185185185,
						7,
						0
					],
					[
						83703.7037037036,
						6,
						0
					],
					[
						83888.8888888888,
						4,
						0
					],
					[
						84074.074074074,
						5,
						0
					],
					[
						84259.2592592592,
						7,
						0
					]
				],
				"typeOfSection": 0,
				"lengthInSteps": 16,
				"gfSection": false,
				"altAnim": false,
				"mustHitSection": false,
				"changeBPM": false,
				"bpm": 165
			},
			{
				"sectionNotes": [
					[
						84444.4444444444,
						0,
						0
					],
					[
						84629.6296296295,
						1,
						0
					],
					[
						84814.8148148147,
						2,
						0
					],
					[
						84999.9999999999,
						1,
						0
					],
					[
						85370.3703703703,
						1,
						0
					],
					[
						85185.1851851851,
						3,
						0
					],
					[
						85555.5555555555,
						2,
						277.777777777778
					],
					[
						85555.5555555555,
						0,
						277.777777777778
					],
					[
						84444.4444444444,
						4,
						0
					],
					[
						84629.6296296295,
						5,
						0
					],
					[
						84814.8148148147,
						6,
						0
					],
					[
						84999.9999999999,
						5,
						0
					],
					[
						85370.3703703703,
						5,
						0
					],
					[
						85185.1851851851,
						7,
						0
					],
					[
						85555.5555555555,
						6,
						277.777777777778
					],
					[
						85555.5555555555,
						4,
						277.777777777778
					]
				],
				"typeOfSection": 0,
				"lengthInSteps": 16,
				"gfSection": false,
				"altAnim": false,
				"mustHitSection": false,
				"changeBPM": false,
				"bpm": 165
			},
			{
				"sectionNotes": [
					[
						85925.9259259258,
						0,
						0
					],
					[
						86018.5185185184,
						1,
						0
					],
					[
						86111.111111111,
						0,
						0
					],
					[
						86203.7037037036,
						3,
						0
					],
					[
						86296.2962962962,
						2,
						0
					],
					[
						86388.8888888888,
						3,
						0
					],
					[
						86481.4814814814,
						1,
						0
					],
					[
						86574.074074074,
						2,
						0
					],
					[
						86666.6666666666,
						1,
						0
					],
					[
						86759.2592592592,
						2,
						0
					],
					[
						86851.8518518518,
						0,
						0
					],
					[
						86944.4444444444,
						1,
						0
					],
					[
						87037.0370370369,
						0,
						0
					],
					[
						87129.6296296295,
						3,
						0
					],
					[
						87222.2222222221,
						2,
						0
					],
					[
						87314.8148148147,
						3,
						0
					]
				],
				"typeOfSection": 0,
				"lengthInSteps": 16,
				"gfSection": false,
				"altAnim": false,
				"mustHitSection": false,
				"changeBPM": false,
				"bpm": 165
			},
			{
				"sectionNotes": [
					[
						87407.4074074073,
						0,
						0
					],
					[
						87499.9999999999,
						1,
						0
					],
					[
						87685.1851851851,
						3,
						0
					],
					[
						87777.7777777777,
						2,
						0
					],
					[
						87962.9629629629,
						0,
						0
					],
					[
						88148.1481481481,
						1,
						0
					],
					[
						88333.3333333332,
						2,
						0
					],
					[
						88518.5185185184,
						3,
						0
					],
					[
						88611.111111111,
						2,
						0
					],
					[
						88703.7037037036,
						1,
						0
					],
					[
						88796.2962962962,
						3,
						0
					]
				],
				"typeOfSection": 0,
				"lengthInSteps": 16,
				"gfSection": false,
				"altAnim": false,
				"mustHitSection": false,
				"changeBPM": false,
				"bpm": 165
			},
			{
				"sectionNotes": [
					[
						88888.8888888888,
						0,
						0
					],
					[
						88981.4814814814,
						1,
						0
					],
					[
						89074.074074074,
						0,
						0
					],
					[
						89166.6666666666,
						3,
						0
					],
					[
						89259.2592592592,
						2,
						0
					],
					[
						89351.8518518518,
						3,
						0
					],
					[
						89444.4444444444,
						1,
						0
					],
					[
						89537.0370370369,
						2,
						0
					],
					[
						89629.6296296295,
						1,
						0
					],
					[
						89722.2222222221,
						2,
						0
					],
					[
						89814.8148148147,
						0,
						0
					],
					[
						89907.4074074073,
						1,
						0
					],
					[
						89999.9999999999,
						0,
						0
					],
					[
						90092.5925925925,
						3,
						0
					],
					[
						90185.1851851851,
						2,
						0
					],
					[
						90277.7777777777,
						3,
						0
					],
					[
						88888.8888888888,
						6,
						277.777777777778
					]
				],
				"typeOfSection": 0,
				"lengthInSteps": 16,
				"gfSection": false,
				"altAnim": false,
				"mustHitSection": true,
				"changeBPM": false,
				"bpm": 165
			},
			{
				"sectionNotes": [
					[
						90370.3703703703,
						0,
						0
					],
					[
						90462.9629629629,
						1,
						0
					],
					[
						90648.1481481481,
						3,
						0
					],
					[
						90740.7407407406,
						2,
						0
					],
					[
						90925.9259259258,
						0,
						0
					],
					[
						91111.111111111,
						1,
						0
					],
					[
						91296.2962962962,
						2,
						0
					],
					[
						91481.4814814814,
						3,
						0
					],
					[
						91574.074074074,
						2,
						0
					],
					[
						91666.6666666666,
						1,
						0
					],
					[
						91759.2592592592,
						3,
						0
					]
				],
				"typeOfSection": 0,
				"lengthInSteps": 16,
				"gfSection": false,
				"altAnim": false,
				"mustHitSection": true,
				"changeBPM": false,
				"bpm": 165
			},
			{
				"sectionNotes": [
					[
						91851.8518518517,
						6,
						277.777777777778
					],
					[
						91851.8518518517,
						0,
						0
					],
					[
						91944.4444444443,
						1,
						0
					],
					[
						92037.0370370369,
						0,
						0
					],
					[
						92129.6296296295,
						2,
						0
					],
					[
						92222.2222222221,
						3,
						0
					],
					[
						92407.4074074073,
						1,
						0
					],
					[
						92314.8148148147,
						2,
						0
					],
					[
						92499.9999999999,
						0,
						0
					],
					[
						92592.5925925925,
						1,
						0
					],
					[
						92777.7777777777,
						2,
						0
					],
					[
						92962.9629629628,
						1,
						0
					],
					[
						93148.148148148,
						2,
						0
					]
				],
				"typeOfSection": 0,
				"lengthInSteps": 16,
				"gfSection": false,
				"altAnim": false,
				"mustHitSection": false,
				"changeBPM": false,
				"bpm": 165
			},
			{
				"sectionNotes": [
					[
						93333.3333333332,
						3,
						0
					],
					[
						93518.5185185184,
						2,
						0
					],
					[
						93703.7037037036,
						0,
						0
					],
					[
						93888.8888888888,
						1,
						0
					],
					[
						93981.4814814814,
						2,
						0
					],
					[
						94074.074074074,
						3,
						0
					],
					[
						94259.2592592591,
						1,
						0
					],
					[
						94166.6666666665,
						2,
						0
					],
					[
						94351.8518518517,
						0,
						0
					],
					[
						94444.4444444443,
						1,
						0
					],
					[
						94629.6296296295,
						3,
						0
					]
				],
				"typeOfSection": 0,
				"lengthInSteps": 16,
				"gfSection": false,
				"altAnim": false,
				"mustHitSection": false,
				"changeBPM": false,
				"bpm": 165
			},
			{
				"sectionNotes": [
					[
						94814.8148148147,
						0,
						0
					],
					[
						94907.4074074073,
						1,
						0
					],
					[
						94999.9999999999,
						0,
						0
					],
					[
						95092.5925925925,
						2,
						0
					],
					[
						95185.1851851851,
						3,
						0
					],
					[
						95370.3703703703,
						1,
						0
					],
					[
						95277.7777777777,
						2,
						0
					],
					[
						95462.9629629628,
						0,
						0
					],
					[
						95555.5555555554,
						1,
						0
					],
					[
						95740.7407407406,
						2,
						0
					],
					[
						95925.9259259258,
						1,
						0
					],
					[
						96111.111111111,
						2,
						0
					]
				],
				"typeOfSection": 0,
				"lengthInSteps": 16,
				"gfSection": false,
				"altAnim": false,
				"mustHitSection": true,
				"changeBPM": false,
				"bpm": 165
			},
			{
				"sectionNotes": [
					[
						96296.2962962962,
						3,
						0
					],
					[
						96481.4814814814,
						2,
						0
					],
					[
						96666.6666666665,
						0,
						0
					],
					[
						96851.8518518517,
						1,
						0
					],
					[
						96944.4444444443,
						2,
						0
					],
					[
						97037.0370370369,
						3,
						0
					],
					[
						97222.2222222221,
						1,
						0
					],
					[
						97129.6296296295,
						2,
						0
					],
					[
						97314.8148148147,
						0,
						0
					],
					[
						97407.4074074073,
						1,
						0
					],
					[
						97592.5925925925,
						3,
						0
					]
				],
				"typeOfSection": 0,
				"lengthInSteps": 16,
				"gfSection": false,
				"altAnim": false,
				"mustHitSection": true,
				"changeBPM": false,
				"bpm": 165
			},
			{
				"sectionNotes": [
					[
						97777.7777777777,
						0,
						0
					],
					[
						97870.3703703703,
						1,
						0
					],
					[
						97962.9629629628,
						0,
						0
					],
					[
						98055.5555555554,
						2,
						0
					],
					[
						98148.148148148,
						3,
						0
					],
					[
						98333.3333333332,
						1,
						0
					],
					[
						98240.7407407406,
						2,
						0
					],
					[
						98425.9259259258,
						0,
						0
					],
					[
						98518.5185185184,
						1,
						0
					],
					[
						98703.7037037036,
						2,
						0
					],
					[
						98888.8888888888,
						1,
						0
					],
					[
						99074.074074074,
						2,
						0
					]
				],
				"typeOfSection": 0,
				"lengthInSteps": 16,
				"gfSection": false,
				"altAnim": false,
				"mustHitSection": false,
				"changeBPM": false,
				"bpm": 165
			},
			{
				"sectionNotes": [
					[
						99259.2592592591,
						3,
						0
					],
					[
						99444.4444444443,
						2,
						0
					],
					[
						99629.6296296295,
						0,
						0
					],
					[
						99814.8148148147,
						1,
						0
					],
					[
						99907.4074074073,
						2,
						0
					],
					[
						99999.9999999999,
						3,
						0
					],
					[
						100185.185185185,
						1,
						0
					],
					[
						100092.592592592,
						2,
						0
					],
					[
						100277.777777778,
						0,
						0
					],
					[
						100370.37037037,
						1,
						0
					],
					[
						100555.555555555,
						3,
						0
					]
				],
				"typeOfSection": 0,
				"lengthInSteps": 16,
				"gfSection": false,
				"altAnim": false,
				"mustHitSection": false,
				"changeBPM": false,
				"bpm": 165
			},
			{
				"lengthInSteps": 16,
				"typeOfSection": 0,
				"sectionNotes": [
					[
						100740.740740741,
						0,
						0
					],
					[
						100833.333333333,
						1,
						0
					],
					[
						100925.925925926,
						0,
						0
					],
					[
						101018.518518518,
						2,
						0
					],
					[
						101111.111111111,
						3,
						0
					],
					[
						101296.296296296,
						1,
						0
					],
					[
						101203.703703704,
						2,
						0
					],
					[
						101388.888888889,
						0,
						0
					],
					[
						101481.481481481,
						1,
						0
					],
					[
						101666.666666667,
						2,
						0
					],
					[
						101851.851851852,
						1,
						0
					],
					[
						102037.037037037,
						2,
						0
					]
				],
				"altAnim": false,
				"gfSection": false,
				"bpm": 165,
				"changeBPM": false,
				"mustHitSection": true
			},
			{
				"lengthInSteps": 16,
				"typeOfSection": 0,
				"sectionNotes": [
					[
						102222.222222222,
						3,
						0
					],
					[
						102407.407407407,
						2,
						0
					],
					[
						102592.592592592,
						0,
						0
					],
					[
						102777.777777778,
						1,
						0
					],
					[
						102870.37037037,
						2,
						0
					],
					[
						102962.962962963,
						3,
						0
					],
					[
						103148.148148148,
						1,
						0
					],
					[
						103055.555555555,
						2,
						0
					],
					[
						103240.740740741,
						0,
						0
					],
					[
						103333.333333333,
						1,
						0
					],
					[
						103518.518518518,
						3,
						0
					]
				],
				"altAnim": false,
				"gfSection": false,
				"bpm": 165,
				"changeBPM": false,
				"mustHitSection": true
			},
			{
				"sectionNotes": [
					[
						103703.703703704,
						2,
						0
					],
					[
						103888.888888889,
						1,
						0
					],
					[
						104074.074074074,
						3,
						0
					],
					[
						104259.259259259,
						0,
						0
					],
					[
						104444.444444444,
						1,
						0
					],
					[
						104537.037037037,
						2,
						0
					],
					[
						104629.629629629,
						1,
						0
					],
					[
						104722.222222222,
						3,
						0
					],
					[
						104814.814814815,
						0,
						277.777777777778
					],
					[
						104814.814814815,
						1,
						277.777777777778
					]
				],
				"typeOfSection": 0,
				"lengthInSteps": 16,
				"gfSection": false,
				"altAnim": false,
				"mustHitSection": false,
				"changeBPM": false,
				"bpm": 165
			},
			{
				"sectionNotes": [
					[
						105185.185185185,
						3,
						0
					],
					[
						105370.37037037,
						2,
						0
					],
					[
						105555.555555555,
						0,
						0
					],
					[
						105740.740740741,
						2,
						0
					],
					[
						105925.925925926,
						3,
						0
					],
					[
						106111.111111111,
						2,
						0
					],
					[
						106296.296296296,
						0,
						0
					],
					[
						106388.888888889,
						1,
						0
					],
					[
						106481.481481481,
						2,
						0
					],
					[
						106574.074074074,
						3,
						0
					]
				],
				"typeOfSection": 0,
				"lengthInSteps": 16,
				"gfSection": false,
				"altAnim": false,
				"mustHitSection": false,
				"changeBPM": false,
				"bpm": 162
			},
			{
				"sectionNotes": [
					[
						106666.666666666,
						2,
						0
					],
					[
						106851.851851852,
						1,
						0
					],
					[
						107037.037037037,
						3,
						0
					],
					[
						107222.222222222,
						0,
						0
					],
					[
						107407.407407407,
						1,
						0
					],
					[
						107500,
						2,
						0
					],
					[
						107592.592592592,
						1,
						0
					],
					[
						107685.185185185,
						3,
						0
					],
					[
						107777.777777778,
						0,
						277.777777777778
					],
					[
						107777.777777778,
						1,
						277.777777777778
					]
				],
				"typeOfSection": 0,
				"lengthInSteps": 16,
				"gfSection": false,
				"altAnim": false,
				"mustHitSection": true,
				"changeBPM": false,
				"bpm": 162
			},
			{
				"sectionNotes": [
					[
						108148.148148148,
						3,
						0
					],
					[
						108333.333333333,
						2,
						0
					],
					[
						108518.518518518,
						0,
						0
					],
					[
						108703.703703704,
						2,
						0
					],
					[
						108888.888888889,
						3,
						0
					],
					[
						109074.074074074,
						2,
						0
					],
					[
						109259.259259259,
						0,
						0
					],
					[
						109351.851851852,
						1,
						0
					],
					[
						109444.444444444,
						2,
						0
					],
					[
						109537.037037037,
						3,
						0
					]
				],
				"typeOfSection": 0,
				"lengthInSteps": 16,
				"gfSection": false,
				"altAnim": false,
				"mustHitSection": true,
				"changeBPM": false,
				"bpm": 162
			},
			{
				"sectionNotes": [
					[
						109629.629629629,
						3,
						0
					]
				],
				"typeOfSection": 0,
				"lengthInSteps": 16,
				"gfSection": false,
				"altAnim": false,
				"mustHitSection": true,
				"changeBPM": false,
				"bpm": 162
			},
			{
				"sectionNotes": [],
				"typeOfSection": 0,
				"lengthInSteps": 16,
				"gfSection": false,
				"altAnim": false,
				"mustHitSection": true,
				"changeBPM": false,
				"bpm": 162
			},
			{
				"lengthInSteps": 16,
				"typeOfSection": 0,
				"sectionNotes": [],
				"altAnim": false,
				"gfSection": false,
				"bpm": 162,
				"changeBPM": false,
				"mustHitSection": true
			},
			{
				"lengthInSteps": 16,
				"typeOfSection": 0,
				"sectionNotes": [],
				"altAnim": false,
				"gfSection": false,
				"bpm": 162,
				"changeBPM": false,
				"mustHitSection": true
			},
			{
				"lengthInSteps": 16,
				"typeOfSection": 0,
				"sectionNotes": [],
				"altAnim": false,
				"gfSection": false,
				"bpm": 162,
				"changeBPM": false,
				"mustHitSection": true
			},
			{
				"lengthInSteps": 16,
				"typeOfSection": 0,
				"sectionNotes": [],
				"altAnim": false,
				"gfSection": false,
				"bpm": 162,
				"changeBPM": false,
				"mustHitSection": true
			},
			{
				"lengthInSteps": 16,
				"typeOfSection": 0,
				"sectionNotes": [],
				"altAnim": false,
				"gfSection": false,
				"bpm": 162,
				"changeBPM": false,
				"mustHitSection": true
			},
			{
				"lengthInSteps": 16,
				"typeOfSection": 0,
				"sectionNotes": [],
				"altAnim": false,
				"gfSection": false,
				"bpm": 162,
				"changeBPM": false,
				"mustHitSection": true
			},
			{
				"lengthInSteps": 16,
				"typeOfSection": 0,
				"sectionNotes": [],
				"altAnim": false,
				"gfSection": false,
				"bpm": 162,
				"changeBPM": false,
				"mustHitSection": true
			},
			{
				"lengthInSteps": 16,
				"typeOfSection": 0,
				"sectionNotes": [],
				"altAnim": false,
				"gfSection": false,
				"bpm": 162,
				"changeBPM": false,
				"mustHitSection": true
			},
			{
				"lengthInSteps": 16,
				"typeOfSection": 0,
				"sectionNotes": [],
				"altAnim": false,
				"gfSection": false,
				"bpm": 162,
				"changeBPM": false,
				"mustHitSection": true
			},
			{
				"lengthInSteps": 16,
				"typeOfSection": 0,
				"sectionNotes": [],
				"altAnim": false,
				"gfSection": false,
				"bpm": 162,
				"changeBPM": false,
				"mustHitSection": true
			},
			{
				"lengthInSteps": 16,
				"typeOfSection": 0,
				"sectionNotes": [],
				"altAnim": false,
				"gfSection": false,
				"bpm": 162,
				"changeBPM": false,
				"mustHitSection": true
			},
			{
				"lengthInSteps": 16,
				"typeOfSection": 0,
				"sectionNotes": [],
				"altAnim": false,
				"gfSection": false,
				"bpm": 162,
				"changeBPM": false,
				"mustHitSection": true
			},
			{
				"lengthInSteps": 16,
				"typeOfSection": 0,
				"sectionNotes": [],
				"altAnim": false,
				"gfSection": false,
				"bpm": 162,
				"changeBPM": false,
				"mustHitSection": true
			},
			{
				"lengthInSteps": 16,
				"typeOfSection": 0,
				"sectionNotes": [],
				"altAnim": false,
				"gfSection": false,
				"bpm": 162,
				"changeBPM": false,
				"mustHitSection": true
			},
			{
				"lengthInSteps": 16,
				"typeOfSection": 0,
				"sectionNotes": [],
				"altAnim": false,
				"gfSection": false,
				"bpm": 162,
				"changeBPM": false,
				"mustHitSection": true
			},
			{
				"sectionNotes": [],
				"typeOfSection": 0,
				"lengthInSteps": 16,
				"gfSection": false,
				"altAnim": false,
				"mustHitSection": true,
				"changeBPM": false,
				"bpm": 162
			},
			{
				"sectionNotes": [],
				"typeOfSection": 0,
				"lengthInSteps": 16,
				"gfSection": false,
				"altAnim": false,
				"mustHitSection": true,
				"changeBPM": false,
				"bpm": 162
			},
			{
				"sectionNotes": [],
				"typeOfSection": 0,
				"lengthInSteps": 16,
				"gfSection": false,
				"altAnim": false,
				"mustHitSection": true,
				"changeBPM": false,
				"bpm": 162
			},
			{
				"sectionNotes": [],
				"typeOfSection": 0,
				"lengthInSteps": 16,
				"gfSection": false,
				"altAnim": false,
				"mustHitSection": true,
				"changeBPM": false,
				"bpm": 162
			},
			{
				"sectionNotes": [],
				"typeOfSection": 0,
				"lengthInSteps": 16,
				"gfSection": false,
				"altAnim": false,
				"mustHitSection": true,
				"changeBPM": false,
				"bpm": 162
			},
			{
				"sectionNotes": [],
				"typeOfSection": 0,
				"lengthInSteps": 16,
				"gfSection": false,
				"altAnim": false,
				"mustHitSection": true,
				"changeBPM": false,
				"bpm": 162
			},
			{
				"sectionNotes": [],
				"typeOfSection": 0,
				"lengthInSteps": 16,
				"gfSection": false,
				"altAnim": false,
				"mustHitSection": true,
				"changeBPM": false,
				"bpm": 162
			},
			{
				"sectionNotes": [],
				"typeOfSection": 0,
				"lengthInSteps": 16,
				"gfSection": false,
				"altAnim": false,
				"mustHitSection": true,
				"changeBPM": false,
				"bpm": 162
			},
			{
				"sectionNotes": [],
				"typeOfSection": 0,
				"lengthInSteps": 16,
				"gfSection": false,
				"altAnim": false,
				"mustHitSection": true,
				"changeBPM": false,
				"bpm": 162
			},
			{
				"sectionNotes": [],
				"typeOfSection": 0,
				"lengthInSteps": 16,
				"gfSection": false,
				"altAnim": false,
				"mustHitSection": true,
				"changeBPM": false,
				"bpm": 162
			},
			{
				"gfSection": false,
				"altAnim": false,
				"typeOfSection": 0,
				"sectionNotes": [],
				"bpm": 162,
				"sectionBeats": 4,
				"changeBPM": false,
				"mustHitSection": true
			},
			{
				"gfSection": false,
				"altAnim": false,
				"typeOfSection": 0,
				"sectionNotes": [],
				"bpm": 162,
				"sectionBeats": 4,
				"changeBPM": false,
				"mustHitSection": true
			}
		],
		"gfVersion": "gf",
		"player3": null,
		"splashSkin": "noteSplashes",
		"song": "Intense",
		"stage": "DoomspireBrickBattle",
		"validScore": true,
		"arrowSkin": "",
		"needsVoices": true,
		"speed": 2.6,
		"bpm": 162
	}
}